risk_rating/__init__.py
risk_rating/risk_rating.py
kyshi_risk_rating-0.2.8.dist-info/LICENSE
kyshi_risk_rating-0.2.8.dist-info/METADATA
kyshi_risk_rating-0.2.8.dist-info/WHEEL
kyshi_risk_rating-0.2.8.dist-info/top_level.txt
kyshi_risk_rating-0.2.8.dist-info/RECORD
