Metadata-Version: 2.1
Name: kyshi-risk-rating
Version: 0.2.8
Summary: Module that handles Kyshi Risk Rating calculation
Home-page: https://github.com/KyshiTransfer/risk-rating.git
Author: raphaelolams
Author-email: raphealolams@gmail.com
License: MIT License
Project-URL: Bug Tracker, https://github.com/KyshiTransfer/risk-rating.git
Platform: UNKNOWN
